{
"backgroundColor"               : null,
"entityColor"                   : "#FFFFFF",
"entityCartoucheColor"          : "#FFFFFF",
"entityCartoucheTextColor"      : "#000000",
"entityAttributeTextColor"      : null,
"entityStrokeColor"             : "#000000",
"associationColor"              : "#FFFFFF",
"associationCartoucheColor"     : "#FFFFFF",
"associationCartoucheTextColor" : "#000000",
"associationAttributeTextColor" : null,
"associationStrokeColor"        : "#000000",
"legStrokeColor"                : "#000000",
"cardTextColor"                 : "#000000",
"labelTextColor"                : "#000000"
}
